torch4d/functional.py
torch4d/torch4d.py
torch4d-0.1.2.dist-info/LICENSE
torch4d-0.1.2.dist-info/METADATA
torch4d-0.1.2.dist-info/WHEEL
torch4d-0.1.2.dist-info/top_level.txt
torch4d-0.1.2.dist-info/RECORD
