Metadata-Version: 2.1
Name: torch4d
Version: 0.1.2
Summary: Implementation of various functional and class 4D methods compatible with PyTorch
Author-email: Firas Darwish <fbd2014@nyu.edu>
License: GNU GENERAL PUBLIC LICENSE
Project-URL: Homepage, https://github.com/FirasBDarwish/PyTorch4D
Project-URL: Repository, https://github.com/FirasBDarwish/PyTorch4D.git
Project-URL: Bug Tracker, https://github.com/FirasBDarwish/PyTorch4D/issues
Keywords: python,package,build,tutorial
Classifier: Programming Language :: Python :: 3
Classifier: Intended Audience :: Education
Classifier: License :: OSI Approved :: GNU General Public License v3 (GPLv3)
Classifier: Operating System :: OS Independent
Requires-Python: >=3.7
License-File: LICENSE
Requires-Dist: termcolor
Requires-Dist: torch
Provides-Extra: dev
Requires-Dist: pytest ; extra == 'dev'
